baytorch/__init__.py
baytorch/bnn.py
baytorch-0.0.1.dev0.dist-info/METADATA
baytorch-0.0.1.dev0.dist-info/WHEEL
baytorch-0.0.1.dev0.dist-info/top_level.txt
baytorch-0.0.1.dev0.dist-info/RECORD
