Metadata-Version: 2.1
Name: baytorch
Version: 0.0.1.dev0
Summary: BayTorch - Bayesian layers for PyTorch
Author-email: "Richard D. Paul" <richard@los-paul.eu>
Classifier: Programming Language :: Python :: 3
Classifier: Operating System :: OS Independent
Requires-Python: >=3.7
